hamsunwoo_lotto/__init__.py
hamsunwoo_lotto/draw.py
hamsunwoo_lotto-0.2.0.dist-info/METADATA
hamsunwoo_lotto-0.2.0.dist-info/WHEEL
hamsunwoo_lotto-0.2.0.dist-info/top_level.txt
hamsunwoo_lotto-0.2.0.dist-info/RECORD
