Metadata-Version: 2.1
Name: hamsunwoo_lotto
Version: 0.2.0
Summary: Default template for PDM package
Author-email: sunwoo <summerham22@gmail.com>
License: MIT
Requires-Python: >=3.9
